{"_type":"export","__export_format":4,"__export_date":"2021-09-18T19:55:03.690Z","__export_source":"insomnia.desktop.app:v2021.5.3","resources":[{"_id":"req_cd6a20bfc7934fa49952216656dd839c","parentId":"fld_ce23534c083140e6818dc9147d1b91ab","modified":1631994350265,"created":1631993649271,"url":"{{ _.baseUrl }}/cities","name":"/","description":"","method":"GET","body":{},"parameters":[{"id":"pair_7b8a7aac4adf461d932346f8ffbae06c","name":"name","value":"Barbalha","description":"","disabled":true},{"id":"pair_bef0253cdf434ce08c12832b94041618","name":"state","value":"SP","description":"","disabled":true}],"headers":[],"authentication":{},"metaSortKey":-1631993649271,"isPrivate":false,"settingStoreCookies":true,"settingSendCookies":true,"settingDisableRenderRequestBody":false,"settingEncodeUrl":true,"settingRebuildPath":true,"settingFollowRedirects":"global","_type":"request"},{"_id":"fld_ce23534c083140e6818dc9147d1b91ab","parentId":"fld_4c9a18ef64764696aa8b2d94b36438d9","modified":1631993467068,"created":1631993467068,"name":"cities","description":"","environment":{},"environmentPropertyOrder":null,"metaSortKey":-1631993467068,"_type":"request_group"},{"_id":"fld_4c9a18ef64764696aa8b2d94b36438d9","parentId":"wrk_249900ace153427abcac72796f9e5e45","modified":1631993458440,"created":1631993458440,"name":"api","description":"","environment":{},"environmentPropertyOrder":null,"metaSortKey":-1631993458440,"_type":"request_group"},{"_id":"wrk_249900ace153427abcac72796f9e5e45","parentId":null,"modified":1631993448260,"created":1631993448260,"name":"compasso-uol-challenge","description":"","scope":"collection","_type":"workspace"},{"_id":"req_4a7f061b42154976bd0b21713758c325","parentId":"fld_ce23534c083140e6818dc9147d1b91ab","modified":1631994313331,"created":1631993478220,"url":"{{ _.baseUrl }}/cities","name":"/","description":"","method":"POST","body":{"mimeType":"application/json","text":"{\n\t\"name\": \"Campinas\",\n\t\"state\": \"SP\"\n}"},"parameters":[],"headers":[{"name":"Content-Type","value":"application/json","id":"pair_fa2c3dfa55c74131b376708d2f63d87e"}],"authentication":{},"metaSortKey":-1631993478220,"isPrivate":false,"settingStoreCookies":true,"settingSendCookies":true,"settingDisableRenderRequestBody":false,"settingEncodeUrl":true,"settingRebuildPath":true,"settingFollowRedirects":"global","_type":"request"},{"_id":"env_c1639a1155383acdd5ce69a4ce5ed6c23cf4e3e9","parentId":"wrk_249900ace153427abcac72796f9e5e45","modified":1631993556797,"created":1631993448272,"name":"Base Environment","data":{},"dataPropertyOrder":{},"color":null,"isPrivate":false,"metaSortKey":1631993448272,"_type":"environment"},{"_id":"jar_c1639a1155383acdd5ce69a4ce5ed6c23cf4e3e9","parentId":"wrk_249900ace153427abcac72796f9e5e45","modified":1631993448278,"created":1631993448278,"name":"Default Jar","cookies":[],"_type":"cookie_jar"},{"_id":"spc_01a08111de3e48db8dbcacfdc3c8bcce","parentId":"wrk_249900ace153427abcac72796f9e5e45","modified":1631993448262,"created":1631993448262,"fileName":"compasso-uol-challenge","contents":"","contentType":"yaml","_type":"api_spec"},{"_id":"env_cb96bd864d6444a8a4233ac9727e993f","parentId":"env_c1639a1155383acdd5ce69a4ce5ed6c23cf4e3e9","modified":1631993577560,"created":1631993530305,"name":"development","data":{"baseUrl":"http://localhost:3333/api"},"dataPropertyOrder":{"&":["baseUrl"]},"color":"#7d69cb","isPrivate":false,"metaSortKey":1631993530305,"_type":"environment"}]}